surf_archiver/__init__.py
surf_archiver/abc.py
surf_archiver/archiver.py
surf_archiver/cli.py
surf_archiver/config.py
surf_archiver/definitions.py
surf_archiver/file.py
surf_archiver/log.py
surf_archiver/main.py
surf_archiver/publisher.py
surf_archiver/remote/__init__.py
surf_archiver/remote/client.py
surf_archiver/remote/main.py
surf_archiver/remote/worker.py
surf_archiver/scripts/init_data.py
surf_archiver/scripts/write_env_file.py
surf_archiver/test_utils.py
surf_archiver/utils.py
surf_archiver-0.1.2.dist-info/METADATA
surf_archiver-0.1.2.dist-info/WHEEL
surf_archiver-0.1.2.dist-info/entry_points.txt
surf_archiver-0.1.2.dist-info/RECORD
