Metadata-Version: 2.3
Name: surf-archiver
Version: 0.1.2
Summary: 
Author: Isaac Williams
Author-email: i.williams@amolf.nl
Requires-Python: >=3.9,<4.0
Classifier: Programming Language :: Python :: 3
Classifier: Programming Language :: Python :: 3.9
Classifier: Programming Language :: Python :: 3.10
Classifier: Programming Language :: Python :: 3.11
Classifier: Programming Language :: Python :: 3.12
Classifier: Programming Language :: Python :: 3.13
Requires-Dist: aio-pika (>=9.4.1,<10.0.0)
Requires-Dist: pydantic (>=2.7.1,<3.0.0)
Requires-Dist: pydantic-settings[yaml] (>=2.2.1,<3.0.0)
Requires-Dist: s3fs (>=2024.3.1,<2025.0.0)
Requires-Dist: typer (>=0.12.3,<0.13.0)
